llama_index/py.typed
llama_index/vector_stores/firestore/__init__.py
llama_index/vector_stores/firestore/base.py
llama_index/vector_stores/firestore/utils.py
llama_index_vector_store_firestore-0.4.1.dist-info/METADATA
llama_index_vector_store_firestore-0.4.1.dist-info/WHEEL
llama_index_vector_store_firestore-0.4.1.dist-info/licenses/LICENSE
llama_index_vector_store_firestore-0.4.1.dist-info/RECORD
