Metadata-Version: 2.4
Name: llama-index-vector-store-firestore
Version: 0.4.1
Summary: llama-index vector_store firestore integration
Author-email: Your Name <you@example.com>
License-Expression: MIT
License-File: LICENSE
Requires-Python: <4.0,>=3.9
Requires-Dist: google-cloud-firestore<3.0.0,>=2.16.0
Requires-Dist: llama-index-core<0.15,>=0.13.0
Requires-Dist: more-itertools<11.0.0,>=10.2.0
